mlexplainer/__init__.py
mlexplainer/core/__init__.py
mlexplainer/core/base_explainer.py
mlexplainer/core/base_predictor.py
mlexplainer/core/base_text_explainer.py
mlexplainer/explainers/__init__.py
mlexplainer/explainers/lime/__init__.py
mlexplainer/explainers/shap/__init__.py
mlexplainer/explainers/shap/binary.py
mlexplainer/explainers/shap/multilabel.py
mlexplainer/explainers/shap/wrapper.py
mlexplainer/interpretation/__init__.py
mlexplainer/interpretation/model_cache.py
mlexplainer/interpretation/text_explainer_llm.py
mlexplainer/interpretation/text_explainer_template.py
mlexplainer/predictors/__init__.py
mlexplainer/predictors/binary_predictor.py
mlexplainer/predictors/multilabel_predictor.py
mlexplainer/utils/__init__.py
mlexplainer/utils/data_processing.py
mlexplainer/utils/quantiles.py
mlexplainer/validation/__init__.py
mlexplainer/validation/feature_interpretation.py
mlexplainer/visualization/__init__.py
mlexplainer/visualization/shap_plots.py
mlexplainer/visualization/target_plots.py
mlexplainer-1.0.2.dist-info/METADATA
mlexplainer-1.0.2.dist-info/WHEEL
mlexplainer-1.0.2.dist-info/licenses/LICENSE
mlexplainer-1.0.2.dist-info/RECORD
