Metadata-Version: 2.4
Name: mlexplainer
Version: 1.0.2
Summary: Advanced Machine Learning package dedicated to model interpretability, with a primary focus on leveraging Shapley values for explaining complex predictive models.
License: MIT
License-File: LICENSE
Author: ZacharieBUISSON
Author-email: zacharie.buisson@orange.fr
Requires-Python: >=3.11,<4.0
Classifier: License :: OSI Approved :: MIT License
Classifier: Programming Language :: Python :: 3
Classifier: Programming Language :: Python :: 3.11
Classifier: Programming Language :: Python :: 3.12
Classifier: Programming Language :: Python :: 3.13
Classifier: Programming Language :: Python :: 3.14
Provides-Extra: llm
Requires-Dist: accelerate (>=1.1.0,<2.0.0) ; extra == "llm"
Requires-Dist: bitsandbytes (>=0.45.0,<0.46.0) ; (sys_platform == "linux") and (extra == "llm")
Requires-Dist: coverage (>=7.8.0,<8.0.0)
Requires-Dist: matplotlib (>=3.10.1,<4.0.0)
Requires-Dist: numpy (>=1.24.2,<3.0.0)
Requires-Dist: pandas (>=2.2.3,<3.0.0)
Requires-Dist: pyarrow (>=19.0.1,<20.0.0)
Requires-Dist: seaborn (>=0.13.2,<0.14.0)
Requires-Dist: shap (>=0.47.1,<0.48.0)
Requires-Dist: torch (>=2.4.0,<3.0.0) ; extra == "llm"
Requires-Dist: transformers (>=4.56.0,<4.57.0) ; extra == "llm"
Requires-Dist: xgboost (>=3.0.4,<4.0.0)
Project-URL: docs, https://mlexplainer.readthedocs.io/en/latest/index.html
Project-URL: repository, https://github.com/ZacharieBuisson1/mlexplainer
